immutablecollections/__init__.py
immutablecollections/_immutabledict.py
immutablecollections/_immutablemultidict.py
immutablecollections/_immutableset.py
immutablecollections/_utils.py
immutablecollections/converter_utils.py
immutablecollections/immutablecollection.py
immutablecollections/py.typed
immutablecollections/version.py
immutablecollections-0.12.0.dist-info/LICENSE
immutablecollections-0.12.0.dist-info/METADATA
immutablecollections-0.12.0.dist-info/WHEEL
immutablecollections-0.12.0.dist-info/top_level.txt
immutablecollections-0.12.0.dist-info/RECORD
