Metadata-Version: 2.1
Name: immutablecollections
Version: 0.12.0
Summary: Immutable Collections (inspired by Google Guava)
Home-page: https://github.com/isi-vista/immutablecollections
Author: Ryan Gabbard <gabbard@isi.edu> and Constantine Lignos <lignos@isi.edu>
Author-email: gabbard@isi.edu
License: UNKNOWN
Platform: UNKNOWN
Classifier: Programming Language :: Python :: 3
Classifier: License :: OSI Approved :: MIT License
Classifier: Operating System :: OS Independent
Requires-Python: ~=3.6
Requires-Dist: typing-extensions
